sqlalchemy_couchdb/__init__.py
sqlalchemy_couchdb/advanced.py
sqlalchemy_couchdb/cache.py
sqlalchemy_couchdb/changes.py
sqlalchemy_couchdb/client.py
sqlalchemy_couchdb/compiler.py
sqlalchemy_couchdb/dialect.py
sqlalchemy_couchdb/exceptions.py
sqlalchemy_couchdb/helpers.py
sqlalchemy_couchdb/management.py
sqlalchemy_couchdb/query_analyzer.py
sqlalchemy_couchdb/replication.py
sqlalchemy_couchdb/retry.py
sqlalchemy_couchdb/types.py
sqlalchemy_couchdb/dbapi/__init__.py
sqlalchemy_couchdb/dbapi/async_.py
sqlalchemy_couchdb/dbapi/base.py
sqlalchemy_couchdb/dbapi/sync.py
sqlalchemy_couchdb/hybrid/__init__.py
sqlalchemy_couchdb/hybrid/dual_write.py
sqlalchemy_couchdb/hybrid/mapper.py
sqlalchemy_couchdb/hybrid/monitor.py
sqlalchemy_couchdb/hybrid/router.py
sqlalchemy_couchdb/orm/__init__.py
sqlalchemy_couchdb/orm/async_session.py
sqlalchemy_couchdb/orm/declarative.py
sqlalchemy_couchdb/orm/relationship.py
sqlalchemy_couchdb/orm/session.py
sqlalchemy_couchdb-0.1.4.dist-info/licenses/LICENSE
sqlalchemy_couchdb-0.1.4.dist-info/METADATA
sqlalchemy_couchdb-0.1.4.dist-info/WHEEL
sqlalchemy_couchdb-0.1.4.dist-info/entry_points.txt
sqlalchemy_couchdb-0.1.4.dist-info/top_level.txt
sqlalchemy_couchdb-0.1.4.dist-info/RECORD
