Metadata-Version: 2.4
Name: sqlalchemy-couchdb
Version: 0.1.4
Summary: SQLAlchemy dialect for CouchDB with async support and hybrid database architecture
Author-email: getaix <develop@getaix.tech>
License-Expression: MIT
Project-URL: Homepage, https://github.com/getaix/sqlalchemy-couchdb
Project-URL: Documentation, https://getaix.github.io/sqlalchemy-couchdb
Project-URL: Repository, https://github.com/getaix/sqlalchemy-couchdb
Project-URL: Issues, https://github.com/getaix/sqlalchemy-couchdb/issues
Keywords: sqlalchemy,couchdb,database,async,nosql,hybrid
Classifier: Development Status :: 3 - Alpha
Classifier: Intended Audience :: Developers
Classifier: Programming Language :: Python :: 3
Classifier: Programming Language :: Python :: 3.11
Classifier: Programming Language :: Python :: 3.12
Classifier: Topic :: Database
Classifier: Topic :: Software Development :: Libraries :: Python Modules
Requires-Python: >=3.11
License-File: LICENSE
Requires-Dist: sqlalchemy>=2.0.0
Requires-Dist: httpx>=0.27.0
Provides-Extra: postgres
Requires-Dist: asyncpg>=0.29.0; extra == "postgres"
Requires-Dist: psycopg2-binary>=2.9.0; extra == "postgres"
Provides-Extra: mysql
Requires-Dist: aiomysql>=0.2.0; extra == "mysql"
Requires-Dist: pymysql>=1.1.0; extra == "mysql"
Provides-Extra: all
Requires-Dist: asyncpg>=0.29.0; extra == "all"
Requires-Dist: psycopg2-binary>=2.9.0; extra == "all"
Requires-Dist: aiomysql>=0.2.0; extra == "all"
Requires-Dist: pymysql>=1.1.0; extra == "all"
Provides-Extra: dev
Requires-Dist: pytest>=7.0.0; extra == "dev"
Requires-Dist: pytest-asyncio>=0.21.0; extra == "dev"
Requires-Dist: pytest-cov>=4.0.0; extra == "dev"
Requires-Dist: black>=23.0.0; extra == "dev"
Requires-Dist: mypy>=1.0.0; extra == "dev"
Requires-Dist: ruff>=0.1.0; extra == "dev"
Dynamic: license-file
